kailo_beewell_dashboard/__init__.py
kailo_beewell_dashboard/about_page.py
kailo_beewell_dashboard/authentication.py
kailo_beewell_dashboard/bar_charts.py
kailo_beewell_dashboard/bar_charts_text.py
kailo_beewell_dashboard/explore_results.py
kailo_beewell_dashboard/grammar.py
kailo_beewell_dashboard/images.py
kailo_beewell_dashboard/import_data.py
kailo_beewell_dashboard/map.py
kailo_beewell_dashboard/page_setup.py
kailo_beewell_dashboard/reshape_data.py
kailo_beewell_dashboard/response_labels.py
kailo_beewell_dashboard/reuse_text.py
kailo_beewell_dashboard/score_descriptions.py
kailo_beewell_dashboard/static_report.py
kailo_beewell_dashboard/stylable_container.py
kailo_beewell_dashboard/summary_rag.py
kailo_beewell_dashboard/switch_page_button.py
kailo_beewell_dashboard/synthesise_aggregate.py
kailo_beewell_dashboard/synthesise_demographic.py
kailo_beewell_dashboard/synthesise_responses.py
kailo_beewell_dashboard/synthesise_scores.py
kailo_beewell_dashboard/topic_labels.py
kailo_beewell_dashboard/who_took_part.py
kailo_beewell_dashboard/css/static_report_style.css
kailo_beewell_dashboard/css/style.css
kailo_beewell_dashboard/images/beewell_map.png
kailo_beewell_dashboard/images/canva_people.png
kailo_beewell_dashboard/images/circle_divider.png
kailo_beewell_dashboard/images/dashboard_home_section.png
kailo_beewell_dashboard/images/devices.png
kailo_beewell_dashboard/images/discovery-looking-researching.jpg
kailo_beewell_dashboard/images/home_image_3_transparent.png
kailo_beewell_dashboard/images/kailo_beewell_logo.png
kailo_beewell_dashboard/images/kailo_beewell_logo_padded.png
kailo_beewell_dashboard/images/kailo_systems_adapted.png
kailo_beewell_dashboard/images/levelling-the-ground.jpg
kailo_beewell_dashboard/images/northern_devon.png
kailo_beewell_dashboard/images/thinking.png
kailo_beewell_dashboard/images/young-person-journey.jpg
kailo_beewell_dashboard/images/symbol_survey/choice.png
kailo_beewell_dashboard/images/symbol_survey/choice_crop.png
kailo_beewell_dashboard-0.3.4.dist-info/LICENSE
kailo_beewell_dashboard-0.3.4.dist-info/METADATA
kailo_beewell_dashboard-0.3.4.dist-info/WHEEL
kailo_beewell_dashboard-0.3.4.dist-info/top_level.txt
kailo_beewell_dashboard-0.3.4.dist-info/RECORD
