Metadata-Version: 2.1
Name: kailo-beewell-dashboard
Version: 0.3.4
Summary: Tools to support creation of #BeeWell survey dashboards for Kailo
Home-page: https://github.com/kailo-beewell/kailo_beewell_dashboard_package
Author: Amy Heather
Author-email: a.heather2@exeter.ac.uk
License: The MIT License (MIT)
Classifier: Programming Language :: Python :: 3.10
Classifier: License :: OSI Approved :: MIT License
Classifier: Operating System :: POSIX :: Linux
License-File: LICENSE
Requires-Dist: pip ==24.0
Requires-Dist: numpy ==1.26.0
Requires-Dist: pandas ==2.1.1
Requires-Dist: plotly ==5.9.0
Requires-Dist: PyMySQL ==1.1.0
Requires-Dist: markdown ==3.5.2
Requires-Dist: kaleido ==0.2.1
Requires-Dist: weasyprint ==60.2
Requires-Dist: django ==4.2.9
Requires-Dist: ipykernel ==6.29.0
Requires-Dist: streamlit >=1.32.2
Requires-Dist: twine ==5.0.0
Requires-Dist: sphinx ==7.2.6
Requires-Dist: sphinx-rtd-theme ==2.0.0
Requires-Dist: myst-parser ==2.0.0
Requires-Dist: sphinx-autoapi ==3.0.0
Requires-Dist: matplotlib ==3.8.3
Requires-Dist: setuptools ==69.1.1
Requires-Dist: wheel ==0.42.0
